jlhfw/__init__.py
jlhfw/version.py
jlhfw/fireworks/__init__.py
jlhfw/fireworks/user_objects/__init__.py
jlhfw/fireworks/user_objects/firetasks/__init__.py
jlhfw/fireworks/user_objects/firetasks/cmd_tasks.py
jlhfw/fireworks/user_objects/firetasks/dataflow_tasks.py
jlhfw/fireworks/user_objects/firetasks/dtool_lookup_tasks.py
jlhfw/fireworks/user_objects/firetasks/dtool_tasks.py
jlhfw/fireworks/user_objects/firetasks/recover_tasks.py
jlhfw/fireworks/user_objects/firetasks/ssh_tasks.py
jlhfw/fireworks/user_objects/firetasks/storage_tasks.py
jlhfw/fireworks/user_objects/firetasks/doc/recover_tasks_1.txt
jlhfw/fireworks/user_objects/firetasks/doc/recover_tasks_2.txt
jlhfw/fireworks/user_objects/firetasks/doc/recover_tasks_3.txt
jlhfw/fireworks/user_objects/firetasks/doc/recover_tasks_4.txt
jlhfw/fireworks/user_objects/firetasks/doc/recover_tasks_5.txt
jlhfw/utils/__init__.py
jlhfw/utils/dict.py
jlhfw/utils/environ.py
jlhfw/utils/logging.py
jlhfw/utils/multiprocessing.py
jlhfw/utils/serialize.py
jlhfw/utils/tracer.py
jlhfw-0.6.0.dist-info/LICENSE
jlhfw-0.6.0.dist-info/METADATA
jlhfw-0.6.0.dist-info/WHEEL
jlhfw-0.6.0.dist-info/top_level.txt
jlhfw-0.6.0.dist-info/RECORD
